impactlab_tools/__init__.py
impactlab_tools/_version.py
impactlab_tools/acp/__init__.py
impactlab_tools/acp/aggregate.py
impactlab_tools/acp/dist.py
impactlab_tools/assets/ACP_county_census_pop.nc
impactlab_tools/assets/GCP_impact_regions.nc
impactlab_tools/assets/__init__.py
impactlab_tools/assets/hierid_regions.dbf
impactlab_tools/assets/hierid_regions.prj
impactlab_tools/assets/hierid_regions.shp
impactlab_tools/assets/hierid_regions.shx
impactlab_tools/assets/weights_acp.csv
impactlab_tools/assets/weights_gcp.csv
impactlab_tools/gcp/__init__.py
impactlab_tools/gcp/dist.py
impactlab_tools/gcp/reindex.py
impactlab_tools/utils/__init__.py
impactlab_tools/utils/binning.py
impactlab_tools/utils/configdict.py
impactlab_tools/utils/files.py
impactlab_tools/utils/paralog.py
impactlab_tools/utils/spatial.py
impactlab_tools/utils/versions.py
impactlab_tools/utils/visualize.py
impactlab_tools/utils/weighting.py
impactlab_tools-0.6.0.dist-info/METADATA
impactlab_tools-0.6.0.dist-info/WHEEL
impactlab_tools-0.6.0.dist-info/licenses/LICENSE
impactlab_tools-0.6.0.dist-info/RECORD
