Metadata-Version: 2.3
Name: impactlab-tools
Version: 0.6.0
Summary: Python tools for Climate Impact Lab developers
Project-URL: Homepage, https://github.com/ClimateImpactLab/impactlab-tools
Project-URL: Bug Tracker, https://github.com/ClimateImpactLab/impactlab-tools/issues
Author-email: Climate Impact Lab <mdelgado@rhg.com>
License-File: LICENSE
Classifier: Intended Audience :: Developers
Classifier: License :: OSI Approved :: MIT License
Classifier: Natural Language :: English
Classifier: Programming Language :: Python :: 3
Requires-Python: >=3.7
Requires-Dist: numpy>=1.7
Requires-Dist: pandas>=0.15
Requires-Dist: pyyaml
Requires-Dist: scipy
Requires-Dist: xarray>=0.8
Provides-Extra: complete
Requires-Dist: geopandas; extra == 'complete'
Requires-Dist: matplotlib; extra == 'complete'
Requires-Dist: pytest-cov>=2.0; extra == 'complete'
Requires-Dist: pytest>=3.0; extra == 'complete'
Requires-Dist: ruff; extra == 'complete'
Requires-Dist: sphinx; extra == 'complete'
Requires-Dist: sphinx-rtd-theme; extra == 'complete'
Provides-Extra: docs
Requires-Dist: sphinx; extra == 'docs'
Requires-Dist: sphinx-rtd-theme; extra == 'docs'
Provides-Extra: test
Requires-Dist: pytest-cov>=2.0; extra == 'test'
Requires-Dist: pytest>=3.0; extra == 'test'
Requires-Dist: ruff; extra == 'test'
Provides-Extra: viz
Requires-Dist: geopandas; extra == 'viz'
Requires-Dist: matplotlib; extra == 'viz'
